pythonic_fp/booleans/__init__.py
pythonic_fp/booleans/flavored.py
pythonic_fp/booleans/py.typed
pythonic_fp/booleans/subtypable.py
pythonic_fp/booleans/truthy_falsy.py
pythonic_fp_booleans-2.0.0.dist-info/licenses/LICENSE
pythonic_fp_booleans-2.0.0.dist-info/WHEEL
pythonic_fp_booleans-2.0.0.dist-info/METADATA
pythonic_fp_booleans-2.0.0.dist-info/RECORD
