Metadata-Version: 2.4
Name: pythonic-fp-booleans
Version: 2.0.0
Summary: Subtypable Boolean Class Hierarchy
Keywords: booleans,subtypable
Author-email: "Geoffrey R. Scheller" <geoffrey@scheller.com>
Requires-Python: >=3.13
Classifier: Development Status :: 4 - Beta
Classifier: Framework :: Pytest
Classifier: Intended Audience :: Developers
Classifier: License :: OSI Approved :: Apache Software License
Classifier: Operating System :: OS Independent
Classifier: Programming Language :: Python :: 3.13
Classifier: Typing :: Typed
License-File: LICENSE
Requires-Dist: pythonic-fp-gadgets>=3.1.0
Requires-Dist: pytest>=8.4.1 ; extra == "test"
Project-URL: Changelog, https://github.com/grscheller/pythonic-fp-booleans/blob/main/CHANGELOG.rst
Project-URL: Documentation, https://grscheller.github.io/pythonic-fp/booleans/development/build/html/
Project-URL: Homepage, https://grscheller.github.io/pythonic-fp/homepage/build/html/
Project-URL: Source, https://github.com/grscheller/pythonic-fp-booleans
Provides-Extra: test
